click_keyring/__init__.py
click_keyring-0.2.1.dist-info/WHEEL
click_keyring-0.2.1.dist-info/METADATA
click_keyring-0.2.1.dist-info/RECORD
