Metadata-Version: 2.1
Name: click-keyring
Version: 0.2.1
Summary: A click option decorator to store and retrieve credentials using keyring.
Home-page: https://github.com/baryonyx5/click-keyring
License: MIT
Author: Kris Seraphine
Author-email: kris.seraphine@gmail.com
Requires-Python: >=3.6
Classifier: Intended Audience :: Developers
Classifier: License :: OSI Approved :: MIT License
Classifier: Operating System :: OS Independent
Classifier: Programming Language :: Python :: 3
Classifier: Programming Language :: Python :: 3.6
Classifier: Programming Language :: Python :: 3.7
Classifier: Programming Language :: Python :: 3.8
Classifier: Programming Language :: Python :: 3.9
Classifier: Topic :: Terminals
Requires-Dist: click (>=7.1.1)
Requires-Dist: cryptography (>=2.9)
Requires-Dist: keyring (>=21.0.0)
